DiscoPlot/__init__.py
DiscoPlot/DiscoPlot.py
DiscoPlot-1.0.2.data/data/LICENSE
DiscoPlot-1.0.2.data/data/README.rst
DiscoPlot-1.0.2.data/data/requirements.txt
DiscoPlot-1.0.2.data/data/docs/DiscoPlot.html
DiscoPlot-1.0.2.data/data/docs/genindex.html
DiscoPlot-1.0.2.data/data/docs/index.html
DiscoPlot-1.0.2.data/data/docs/modules.html
DiscoPlot-1.0.2.data/data/docs/objects.inv
DiscoPlot-1.0.2.data/data/docs/search.html
DiscoPlot-1.0.2.data/data/docs/searchindex.js
DiscoPlot-1.0.2.data/data/docs/_sources/DiscoPlot.txt
DiscoPlot-1.0.2.data/data/docs/_sources/index.txt
DiscoPlot-1.0.2.data/data/docs/_sources/modules.txt
DiscoPlot-1.0.2.data/data/docs/_static/ajax-loader.gif
DiscoPlot-1.0.2.data/data/docs/_static/basic.css
DiscoPlot-1.0.2.data/data/docs/_static/comment-bright.png
DiscoPlot-1.0.2.data/data/docs/_static/comment-close.png
DiscoPlot-1.0.2.data/data/docs/_static/comment.png
DiscoPlot-1.0.2.data/data/docs/_static/default.css
DiscoPlot-1.0.2.data/data/docs/_static/doctools.js
DiscoPlot-1.0.2.data/data/docs/_static/down-pressed.png
DiscoPlot-1.0.2.data/data/docs/_static/down.png
DiscoPlot-1.0.2.data/data/docs/_static/file.png
DiscoPlot-1.0.2.data/data/docs/_static/jquery.js
DiscoPlot-1.0.2.data/data/docs/_static/minus.png
DiscoPlot-1.0.2.data/data/docs/_static/plus.png
DiscoPlot-1.0.2.data/data/docs/_static/pygments.css
DiscoPlot-1.0.2.data/data/docs/_static/searchtools.js
DiscoPlot-1.0.2.data/data/docs/_static/sidebar.js
DiscoPlot-1.0.2.data/data/docs/_static/underscore.js
DiscoPlot-1.0.2.data/data/docs/_static/up-pressed.png
DiscoPlot-1.0.2.data/data/docs/_static/up.png
DiscoPlot-1.0.2.data/data/docs/_static/websupport.js
DiscoPlot-1.0.2.data/scripts/DiscoPlot
DiscoPlot-1.0.2.dist-info/DESCRIPTION.rst
DiscoPlot-1.0.2.dist-info/METADATA
DiscoPlot-1.0.2.dist-info/metadata.json
DiscoPlot-1.0.2.dist-info/RECORD
DiscoPlot-1.0.2.dist-info/top_level.txt
DiscoPlot-1.0.2.dist-info/WHEEL
