Metadata-Version: 2.0
Name: DiscoPlot
Version: 1.0.2
Summary: DiscoPlot: identify genomic rearrangements, misassemblies and sequencing artefacts in NGS data
Home-page: https://github.com/BeatsonLab-MicrobialGenomics/DiscoPlot
Author: Mitchell Sullivan
Author-email: mjsull@gmail.com
License: GPLv3
Platform: UNKNOWN
Classifier: Development Status :: 4 - Beta
Classifier: Environment :: X11 Applications
Classifier: Intended Audience :: Science/Research
Classifier: License :: OSI Approved
Classifier: Natural Language :: English
Classifier: Operating System :: POSIX :: Linux
Classifier: Programming Language :: Python
Classifier: Programming Language :: Python :: 2.7
Classifier: Programming Language :: Python :: 2 :: Only
Classifier: Topic :: Scientific/Engineering :: Bio-Informatics
Classifier: Topic :: Scientific/Engineering :: Visualization
Requires-Dist: numpy (==1.8.1)
Requires-Dist: matplotlib (==1.3.1)
Requires-Dist: pysam (==0.8.1)
